qd/__init__.py
qd_plot-0.0.3.dist-info/LICENSE
qd_plot-0.0.3.dist-info/METADATA
qd_plot-0.0.3.dist-info/WHEEL
qd_plot-0.0.3.dist-info/entry_points.txt
qd_plot-0.0.3.dist-info/top_level.txt
qd_plot-0.0.3.dist-info/RECORD
