Metadata-Version: 2.1
Name: qd-plot
Version: 0.0.3
Summary: quickdraw - a cli plotting tool
Home-page: https://github.com/velicanu/qd
Author: Dragos Velicanu
Author-email: qd@velicanu.com
License: MIT
Platform: UNKNOWN
Classifier: License :: OSI Approved :: MIT License
Classifier: Programming Language :: Python :: 3
Classifier: Programming Language :: Python :: 3.10
Requires-Dist: click
Requires-Dist: imgcat
Requires-Dist: kaleido
Requires-Dist: pandas
Requires-Dist: plotly
